dj_backup/__init__.py
dj_backup/admin.py
dj_backup/apps.py
dj_backup/config.py
dj_backup/forms.py
dj_backup/notification.py
dj_backup/signals.py
dj_backup/urls.py
dj_backup/views.py
dj_backup/core/__init__.py
dj_backup/core/logging.py
dj_backup/core/mixins.py
dj_backup/core/tasks.py
dj_backup/core/triggers.py
dj_backup/core/backup/__init__.py
dj_backup/core/backup/base.py
dj_backup/core/backup/file.py
dj_backup/core/backup/db/__init__.py
dj_backup/core/backup/db/base.py
dj_backup/core/backup/db/mysql.py
dj_backup/core/backup/db/postgresql.py
dj_backup/core/backup/db/sqlite.py
dj_backup/core/storages/__init__.py
dj_backup/core/storages/base.py
dj_backup/core/storages/drop_box.py
dj_backup/core/storages/ftp_server.py
dj_backup/core/storages/local.py
dj_backup/core/storages/sftp_server.py
dj_backup/core/storages/telegram_bot.py
dj_backup/core/task/__init__.py
dj_backup/core/task/common.py
dj_backup/core/task/runner.py
dj_backup/core/task/schedule.py
dj_backup/core/utils/__init__.py
dj_backup/core/utils/static.py
dj_backup/core/utils/secure/__init__.py
dj_backup/core/utils/secure/aes.py
dj_backup/core/utils/secure/base.py
dj_backup/core/utils/secure/zipp.py
dj_backup/core/utils/secure/scripts/decrypt_aes.py
dj_backup/management/__init__.py
dj_backup/management/commands/__init__.py
dj_backup/management/commands/run-backup.py
dj_backup/migrations/0001_initial.py
dj_backup/migrations/0002_djbackupsecure.py
dj_backup/migrations/0003_rename_t_djbackupsecure_encryption_type.py
dj_backup/migrations/0004_rename_djbackuploglevel_djbackuploglevelnotif.py
dj_backup/migrations/__init__.py
dj_backup/models/__init__.py
dj_backup/models/base.py
dj_backup/models/notification.py
dj_backup/static/dj_backup/assets/css/dashlite.css
dj_backup/static/dj_backup/assets/css/notify.css
dj_backup/static/dj_backup/assets/css/libs/bootstrap-icons.css
dj_backup/static/dj_backup/assets/css/libs/fontawesome-icons.css
dj_backup/static/dj_backup/assets/css/libs/themify-icons.css
djbackup-2.3.2.dist-info/METADATA
djbackup-2.3.2.dist-info/WHEEL
djbackup-2.3.2.dist-info/top_level.txt
djbackup-2.3.2.dist-info/RECORD
