Metadata-Version: 2.4
Name: djbackup
Version: 2.3.2
Summary: djbackup(django backup) is an installable module for Django that is used for backup purposes, specifically for backing up the database and media files.
Home-page: https://github.com/FZl47/dj_backup
Author: FZl47
Author-email: fzl8747@gmail.com
Keywords: django,database,media,backup,dropbox,ftp,sftp,mysql,postgresql,sqlite
Classifier: Development Status :: 5 - Production/Stable
Classifier: Environment :: Web Environment
Classifier: Framework :: Django
Classifier: Intended Audience :: Developers
Classifier: Intended Audience :: System Administrators
Classifier: License :: OSI Approved :: MIT License
Classifier: Operating System :: OS Independent
Classifier: Programming Language :: Python :: 3
Classifier: Topic :: Database
Classifier: Topic :: System :: Archiving
Classifier: Topic :: System :: Archiving :: Backup
Classifier: Topic :: System :: Archiving :: Compression
Requires-Dist: APScheduler==3.11.0
Requires-Dist: asgiref==3.8.1
Requires-Dist: django-model-utils==5.0.0
Requires-Dist: sqlparse
Requires-Dist: tzdata
Requires-Dist: tzlocal
Requires-Dist: pycryptodome
Requires-Dist: pyzipper
Provides-Extra: telegram
Requires-Dist: python-telegram-bot; extra == "telegram"
Provides-Extra: sftpserver
Requires-Dist: paramiko; extra == "sftpserver"
Provides-Extra: ftpserver
Requires-Dist: ftplib; extra == "ftpserver"
Provides-Extra: dropbox
Requires-Dist: dropbox; extra == "dropbox"
Provides-Extra: mysql
Requires-Dist: mysqlclient; extra == "mysql"
Provides-Extra: postgresql
Requires-Dist: psycopg2; extra == "postgresql"
Provides-Extra: all
Requires-Dist: python-telegram-bot; extra == "all"
Requires-Dist: paramiko; extra == "all"
Requires-Dist: ftplib; extra == "all"
Requires-Dist: dropbox; extra == "all"
Requires-Dist: mysqlclient; extra == "all"
Requires-Dist: psycopg2; extra == "all"
Dynamic: author
Dynamic: author-email
Dynamic: classifier
Dynamic: description
Dynamic: description-content-type
Dynamic: home-page
Dynamic: keywords
Dynamic: provides-extra
Dynamic: requires-dist
Dynamic: summary
